.gitignore
README.md
setup.py
.idea/.gitignore
.idea/colorply.iml
.idea/misc.xml
.idea/modules.xml
.idea/vcs.xml
.idea/inspectionProfiles/profiles_settings.xml
colorply/__init__.py
colorply.egg-info/PKG-INFO
colorply.egg-info/SOURCES.txt
colorply.egg-info/dependency_links.txt
colorply.egg-info/not-zip-safe
colorply.egg-info/requires.txt
colorply.egg-info/top_level.txt
colorply/io/__init__.py
colorply/io/imfile.py
colorply/io/ply.py
colorply/io/readxml.py
colorply/mm3d/__init__.py
colorply/mm3d/calibration.py
colorply/mm3d/functional.py
colorply/process/__init__.py
colorply/process/image.py
colorply/process/imformula.py
colorply/process/improcess.py
colorply/ui/__init__.py
colorply/ui/call.py
colorply/ui/gui.py
colorply/ui/palette.py
colorply/util/__init__.py
colorply/util/util.py