Metadata-Version: 2.1
Name: colorply
Version: 0.0.1
Summary: MicMac application for multispectral photogrammetry.
Home-page: https://github.com/arthurdjn/colorply
Author: Arthur Dujardin, Cédric Périon
Author-email: arthur.dujardin@ensg.eu
License: MIT
Platform: UNKNOWN
Classifier: Development Status :: 5 - Production/Stable
Classifier: Intended Audience :: Developers
Classifier: Topic :: Software Development :: Build Tools
Classifier: Programming Language :: Python :: 3
